pyAesCrypt/__init__.py
pyAesCrypt/crypto.py
pyAesCrypt/test_crypto.py
pyAesCrypt-6.1.0.data/scripts/pyAesCrypt
pyAesCrypt-6.1.0.dist-info/LICENSE
pyAesCrypt-6.1.0.dist-info/METADATA
pyAesCrypt-6.1.0.dist-info/WHEEL
pyAesCrypt-6.1.0.dist-info/top_level.txt
pyAesCrypt-6.1.0.dist-info/RECORD
