Metadata-Version: 2.1
Name: pyAesCrypt
Version: 6.1.0
Summary: Encrypt and decrypt files and streams in AES Crypt format (version 2)
Home-page: https://github.com/marcobellaccini/pyAesCrypt
Author: Marco Bellaccini
License: Apache License 2.0
Keywords: AES Crypt encrypt decrypt
Classifier: License :: OSI Approved :: Apache Software License
Classifier: Operating System :: OS Independent
Classifier: Programming Language :: Python :: 3
Classifier: Topic :: Security
Classifier: Topic :: Security :: Cryptography
Classifier: Topic :: Utilities
License-File: LICENSE
Requires-Dist: cryptography
